{
  "type": "FeatureCollection",
  "features": [
    {
      "type": "Feature",
      "geometry": {
        "type": "Point",
        "coordinates": [
          57.117224,
          28.650325
        ]
      },
      "properties": {
        "id": "mindat_287886",
        "name": "Esfandaqeh, Jiroft County, Kerman Province, Iran",
        "type": "529",
        "country": "Iran",
        "description": "<h3>Esfandaqeh, Jiroft County, Kerman Province, Iran</h3>\n<p><strong>Type:</strong> 529</p>\n<p><strong>Location:</strong> Iran</p>\n<p>Esfandaqeh Rural District (Persian: دهستان اسفندقه) is a rural district (dehestan) in the Central District of Jiroft County, Kerman Province, Iran.\r\n\r\nThe rural district has 52 villages.</p>\n<p><a href=\"https://www.mindat.org/loc-287886.html\" target=\"_blank\">View on Mindat.org</a></p>",
        "geomaterials": [
          "Barite",
          "Calcite",
          "Chalcopyrite",
          "Fluorite",
          "Iron",
          "Iron_Oxide",
          "Limonite",
          "Magnetite",
          "Malachite",
          "Material_1016",
          "Material_1036",
          "Material_1437",
          "Material_234",
          "Material_3037",
          "Material_3155",
          "Material_3758",
          "Material_3911",
          "Material_3924",
          "Material_3991",
          "Material_8658",
          "Material_9252",
          "Molybdenite",
          "Quartz",
          "Sphalerite",
          "Tetrahedrite"
        ],
        "marker_type": "default"
      }
    }
  ]
}