{
  "type": "FeatureCollection",
  "features": [
    {
      "type": "Feature",
      "geometry": {
        "type": "Point",
        "coordinates": [
          45.416666666667,
          36.5
        ]
      },
      "properties": {
        "id": "mindat_276466",
        "name": "Piranshahr intrusion (Piranshahr massif), Piranshahr County, West Azerbaijan Province, Iran",
        "type": "323",
        "country": "Iran",
        "description": "<h3>Piranshahr intrusion (Piranshahr massif), Piranshahr County, West Azerbaijan Province, Iran</h3>\n<p><strong>Type:</strong> 323</p>\n<p><strong>Location:</strong> Iran</p>\n<p>Intrusion c.16x10 km in extent emplaced into Mesozoic limestones and pelites.</p>\n<p><a href=\"https://www.mindat.org/loc-276466.html\" target=\"_blank\">View on Mindat.org</a></p>",
        "geomaterials": [
          "Calcite",
          "Chalcopyrite",
          "Fluorite",
          "Gersdorffite",
          "Iron",
          "Lead",
          "Limonite",
          "Magnetite",
          "Malachite",
          "Material_1168",
          "Material_118",
          "Material_1294",
          "Material_1365",
          "Material_1384",
          "Material_1458",
          "Material_1624",
          "Material_1720",
          "Material_1740",
          "Material_1842",
          "Material_2013",
          "Material_207",
          "Material_2129",
          "Material_2402",
          "Material_241",
          "Material_2538",
          "Material_2571",
          "Material_2750",
          "Material_2880",
          "Material_29229",
          "Material_31",
          "Material_3119",
          "Material_3304",
          "Material_3328",
          "Material_3418",
          "Material_3486",
          "Material_3688",
          "Material_3924",
          "Material_3946",
          "Material_3978",
          "Material_419",
          "Material_43733",
          "Material_4421",
          "Material_46220",
          "Material_6613",
          "Material_6683",
          "Material_677",
          "Material_8658",
          "Material_8789",
          "Material_9252",
          "Material_9264",
          "Material_934",
          "Material_9767",
          "Molybdenite",
          "Pyrite",
          "Quartz",
          "Sphalerite"
        ],
        "marker_type": "default"
      }
    },
    {
      "type": "Feature",
      "geometry": {
        "type": "Point",
        "coordinates": [
          55.84616299102,
          29.977614022549
        ]
      },
      "properties": {
        "id": "mindat_424764",
        "name": "Sar Cheshmeh Smelter, Pariz, Sirjan County, Kerman Province, Iran",
        "type": "41",
        "country": "Iran",
        "geomaterials": [
          "Calcite",
          "Covellite",
          "Iron",
          "Material_1458",
          "Material_2538",
          "Material_3328",
          "Material_4029",
          "Pyrite"
        ],
        "description": "<h3>Sar Cheshmeh Smelter, Pariz, Sirjan County, Kerman Province, Iran</h3>\n<p><strong>Type:</strong> 41</p>\n<p><strong>Location:</strong> Iran</p>\n<p><a href=\"https://www.mindat.org/loc-424764.html\" target=\"_blank\">View on Mindat.org</a></p>",
        "marker_type": "default"
      }
    }
  ]
}